onnxocr/__init__.py
onnxocr/cls_postprocess.py
onnxocr/db_postprocess.py
onnxocr/imaug.py
onnxocr/logger.py
onnxocr/onnx_paddleocr.py
onnxocr/operators.py
onnxocr/predict_base.py
onnxocr/predict_cls.py
onnxocr/predict_det.py
onnxocr/predict_rec.py
onnxocr/predict_system.py
onnxocr/rec_postprocess.py
onnxocr/utils.py
onnxocr/fonts/simfang.ttf
onnxocr/models/ppocrv5/ppocrv5_dict.txt
onnxocr/models/ppocrv5/cls/cls.onnx
onnxocr/models/ppocrv5/det/det.onnx
onnxocr/models/ppocrv5/rec/rec.onnx
ydocr_onnx-1.0.2.dist-info/LICENSE
ydocr_onnx-1.0.2.dist-info/METADATA
ydocr_onnx-1.0.2.dist-info/WHEEL
ydocr_onnx-1.0.2.dist-info/top_level.txt
ydocr_onnx-1.0.2.dist-info/RECORD
