Metadata-Version: 2.1
Name: ydocr-onnx
Version: 1.0.2
Summary: 基于 PaddleOCR 的离线 OCR 识别工具，使用 ONNX 模型进行推理
Home-page: https://github.com/yourusername/ydocr-onnx
Author: jiaer
Author-email: jia.er@winrobot360.com
License: Apache 2.0
Classifier: Development Status :: 4 - Beta
Classifier: Intended Audience :: Developers
Classifier: Topic :: Scientific/Engineering :: Image Recognition
Classifier: Programming Language :: Python :: 3
Classifier: Programming Language :: Python :: 3.7
Classifier: Programming Language :: Python :: 3.8
Classifier: Programming Language :: Python :: 3.9
Classifier: License :: OSI Approved :: Apache Software License
Classifier: Operating System :: OS Independent
License-File: LICENSE
Requires-Dist: opencv-python-headless (>=4.7)
Requires-Dist: onnxruntime (>=1.14)
Requires-Dist: numpy
Requires-Dist: requests
Requires-Dist: shapely
Requires-Dist: pyclipper
Requires-Dist: scikit-image
